{
  "heading": "2024 Pit Scout Form",
  "skipTeamSelection": true,
  "pages": [
    {
      "name": "Physical Characteristics",
      "widgets": [
        {
          "name": "Drivetrain",
          "type": "radio",
          "options": [
            "COTS Swerve (SDS)",
            "COTS Swerve (WCP)",
            "COTS Swerve (REV)",
            "COTS Swerve (Thrifty)",
            "Custom Swerve",
            "Kit of Parts",
            "Custom WCD",
            "Mecanum",
            "Other"
          ]
        },
        {
          "name": "Robot Height (inches)",
          "type": "number"
        }
      ]
    },
    {
      "name": "Capabilities",
      "widgets": [
        {
          "name": "Pickup Locations",
          "type": "multicheckbox",
          "options": [
            "Floor",
            "Source"
          ]
        }
      ]
    },
    {
      "name": "Contact Info",
      "widgets": [
        {
          "name": "Contact Phone Number for Alliance Selection",
          "type": "text"
        }
      ]
    }
  ]
}
